mickjagger/__init__.py
mickjagger/fonction_graphe_network.py
mickjagger/main.py
mickjagger-1.0.dist-info/LICENSE.txt
mickjagger-1.0.dist-info/METADATA
mickjagger-1.0.dist-info/WHEEL
mickjagger-1.0.dist-info/top_level.txt
mickjagger-1.0.dist-info/RECORD
