Metadata-Version: 2.1
Name: mickjagger
Version: 1.0
Summary: A package for times series evolution graphics
Home-page: https://github.com/gabsens/Python-for-Data-Scientists-ENSAE
Author: groupe_mickjagger
Author-email: afanboj1@gmail.com
License: UNKNOWN
Platform: UNKNOWN
Classifier: Programming Language :: Python :: 3
Classifier: License :: OSI Approved :: MIT License
Classifier: Operating System :: OS Independent
Requires-Python: >=3.5
